{"id": "_pytest.outcomes", "path": "/home/vscode/.local/lib/python3.11/site-packages/_pytest/outcomes.py", "mtime": 1668613472, "size": 10086, "hash": "444a9dc25ef3ac3dccee2051c4f0655d011c02cd60674ef2e04f186a0a71a718", "data_mtime": 1668600369, "dependencies": ["_pytest.deprecated", "_pytest.config", "packaging.version", "sys", "warnings", "typing", "typing_extensions", "pytest", "builtins", "_ast", "_pytest.config.exceptions", "_pytest.warning_types", "_warnings", "abc", "array", "ctypes", "mmap", "packaging", "pickle", "types"], "suppressed": [], "options": {"warn_no_return": true, "always_false": [], "warn_unused_ignores": true, "ignore_missing_imports": true, "disabled_error_codes": [], "disable_error_code": [], "disallow_untyped_defs": true, "disallow_any_generics": true, "no_implicit_optional": true, "plugins": [], "disallow_incomplete_defs": true, "strict_optional_whitelist": null, "local_partial_types": false, "always_true": [], "follow_imports_for_stubs": false, "disallow_untyped_calls": true, "strict_equality": true, "follow_imports": "silent", "check_untyped_defs": true, "ignore_errors": false, "implicit_reexport": false, "enabled_error_codes": [], "mypyc": false, "bazel": false, "platform": "linux", "strict_optional": true, "allow_redefinition": false, "disallow_subclassing_any": true, "disallow_untyped_decorators": true, "show_none_errors": true, "allow_untyped_globals": false, "warn_unreachable": false, "disallow_any_expr": false, "disallow_any_decorated": false, "disallow_any_unimported": false, "enable_error_code": [], "warn_return_any": true, "strict_concatenate": true, "disallow_any_explicit": false}, "dep_prios": [5, 20, 20, 10, 10, 5, 25, 20, 5, 30, 30, 30, 30, 30, 30, 30, 30, 30, 30, 30], "dep_lines": [13, 132, 300, 3, 4, 5, 18, 224, 1, 1, 1, 1, 1, 1, 1, 1, 1, 1, 1, 1], "interface_hash": "53e1057c1daa5d1abdd76fd7ebabc62d7453ce00faddd2c664ba7ef43764831e", "version_id": "0.982", "ignore_all": true, "plugin_data": null}